setup.cfg
setup.py
pyripple/__init__.py
python_ripple_api.egg-info/PKG-INFO
python_ripple_api.egg-info/SOURCES.txt
python_ripple_api.egg-info/dependency_links.txt
python_ripple_api.egg-info/requires.txt
python_ripple_api.egg-info/top_level.txt
python_ripple_api.egg-info/zip-safe