Metadata-Version: 1.0
Name: python-ripple-api
Version: 0.0.3
Summary: Python API for interacting with ripple.com.
Home-page: https://github.com/nkgilley/python-ripple-api
Author: Nolan Gilley
Author-email: nkgilley@gmail.com
License: MIT
Platform: UNKNOWN
